{
	"documents": [
		{
			"address_name": "서울 강남구 일원동 687-6",
			"category_group_code": "FD6",
			"category_group_name": "음식점",
			"category_name": "음식점 \u003e 아시아음식 \u003e 동남아음식 \u003e 베트남음식",
			"distance": "643",
			"id": "365614344",
			"phone": "",
			"place_name": "분타 일원점",
			"place_url": "http://place.map.kakao.com/365614344",
			"road_address_name": "서울 강남구 일원로9길 16",
			"x": "127.082900146248",
			"y": "37.4895947077571"
		},
		{
			"address_name": "서울 강남구 개포동 14-5",
			"category_group_code": "FD6",
			"category_group_name": "음식점",
			"category_name": "음식점 \u003e 아시아음식 \u003e 동남아음식",
			"distance": "1206",
			"id": "17078980",
			"phone": "02-445-8188",
			"place_name": "포나타이",
			"place_url": "http://place.map.kakao.com/17078980",
			"road_address_name": "서울 강남구 개포로 621",
			"x": "127.078893980736",
			"y": "37.4939358003886"
		},
		{
			"address_name": "서울 강남구 수서동 713",
			"category_group_code": "FD6",
			"category_group_name": "음식점",
			"category_name": "음식점 \u003e 아시아음식 \u003e 동남아음식 \u003e 베트남음식",
			"distance": "1641",
			"id": "2063362351",
			"phone": "02-2040-6088",
			"place_name": "월미당 수서역점",
			"place_url": "http://place.map.kakao.com/2063362351",
			"road_address_name": "서울 강남구 밤고개로1길 10",
			"x": "127.101844676517",
			"y": "37.4880247568559"
		},
		{
			"address_name": "서울 강남구 수서동 714",
			"category_group_code": "FD6",
			"category_group_name": "음식점",
			"category_name": "음식점 \u003e 술집 \u003e 호프,요리주점",
			"distance": "1700",
			"id": "23108244",
			"phone": "02-3411-9436",
			"place_name": "더리얼펍 수서점",
			"place_url": "http://place.map.kakao.com/23108244",
			"road_address_name": "서울 강남구 광평로51길 8",
			"x": "127.102380075954",
			"y": "37.4884432626246"
		},
		{
			"address_name": "서울 강남구 수서동 724",
			"category_group_code": "FD6",
			"category_group_name": "음식점",
			"category_name": "음식점 \u003e 아시아음식 \u003e 동남아음식 \u003e 베트남음식",
			"distance": "1730",
			"id": "627816447",
			"phone": "02-3411-4173",
			"place_name": "포시애틀 수서역점",
			"place_url": "http://place.map.kakao.com/627816447",
			"road_address_name": "서울 강남구 광평로 280",
			"x": "127.103107846193",
			"y": "37.4873190732529"
		},
		{
			"address_name": "서울 강남구 수서동 714-4",
			"category_group_code": "FD6",
			"category_group_name": "음식점",
			"category_name": "음식점 \u003e 아시아음식 \u003e 동남아음식",
			"distance": "1772",
			"id": "12503564",
			"phone": "02-445-7131",
			"place_name": "포메인 수서점",
			"place_url": "http://place.map.kakao.com/12503564",
			"road_address_name": "서울 강남구 광평로51길 6-11",
			"x": "127.103212370274",
			"y": "37.4885038069698"
		},
		{
			"address_name": "서울 강남구 자곡동 650",
			"category_group_code": "FD6",
			"category_group_name": "음식점",
			"category_name": "음식점 \u003e 분식",
			"distance": "2018",
			"id": "1825544041",
			"phone": "",
			"place_name": "미스타쌀국수 자곡점",
			"place_url": "http://place.map.kakao.com/1825544041",
			"road_address_name": "서울 강남구 자곡로 172",
			"x": "127.1025662342069",
			"y": "37.47325389690811"
		},
		{
			"address_name": "서울 강남구 자곡동 653",
			"category_group_code": "FD6",
			"category_group_name": "음식점",
			"category_name": "음식점 \u003e 아시아음식",
			"distance": "2059",
			"id": "1929907694",
			"phone": "",
			"place_name": "타이완벤땅 수서자곡점",
			"place_url": "http://place.map.kakao.com/1929907694",
			"road_address_name": "서울 강남구 자곡로 186",
			"x": "127.10365350606223",
			"y": "37.473882753974735"
		},
		{
			"address_name": "서울 강남구 대치동 994-8",
			"category_group_code": "FD6",
			"category_group_name": "음식점",
			"category_name": "음식점 \u003e 아시아음식 \u003e 동남아음식 \u003e 베트남음식",
			"distance": "2169",
			"id": "8856913",
			"phone": "02-564-7879",
			"place_name": "다낭월남쌈",
			"place_url": "http://place.map.kakao.com/8856913",
			"road_address_name": "서울 강남구 영동대로 221",
			"x": "127.068151212348",
			"y": "37.4987754849712"
		},
		{
			"address_name": "서울 강남구 대치동 316",
			"category_group_code": "FD6",
			"category_group_name": "음식점",
			"category_name": "음식점 \u003e 아시아음식 \u003e 동남아음식",
			"distance": "2188",
			"id": "1950750099",
			"phone": "",
			"place_name": "은마쌀국수",
			"place_url": "http://place.map.kakao.com/1950750099",
			"road_address_name": "서울 강남구 삼성로 212",
			"x": "127.06379205126",
			"y": "37.4952243499392"
		},
		{
			"address_name": "서울 강남구 대치동 316",
			"category_group_code": "FD6",
			"category_group_name": "음식점",
			"category_name": "음식점 \u003e 아시아음식 \u003e 동남아음식 \u003e 베트남음식",
			"distance": "2196",
			"id": "701196358",
			"phone": "",
			"place_name": "홍대쌀국수 은마점",
			"place_url": "http://place.map.kakao.com/701196358",
			"road_address_name": "서울 강남구 삼성로 212",
			"x": "127.063742353225",
			"y": "37.4952928532742"
		},
		{
			"address_name": "서울 강남구 대치동 507-1",
			"category_group_code": "FD6",
			"category_group_name": "음식점",
			"category_name": "음식점 \u003e 아시아음식 \u003e 동남아음식 \u003e 베트남음식",
			"distance": "2204",
			"id": "11409033",
			"phone": "02-567-5956",
			"place_name": "포카이",
			"place_url": "http://place.map.kakao.com/11409033",
			"road_address_name": "서울 강남구 남부순환로 2942",
			"x": "127.062325189202",
			"y": "37.4936429649011"
		},
		{
			"address_name": "서울 강남구 세곡동 600",
			"category_group_code": "FD6",
			"category_group_name": "음식점",
			"category_name": "음식점 \u003e 한식 \u003e 육류,고기 \u003e 갈비",
			"distance": "2233",
			"id": "873107326",
			"phone": "02-451-7988",
			"place_name": "오세안 양갈비",
			"place_url": "http://place.map.kakao.com/873107326",
			"road_address_name": "서울 강남구 헌릉로569길 39",
			"x": "127.097405070204",
			"y": "37.4667971188175"
		},
		{
			"address_name": "서울 강남구 대치동 622",
			"category_group_code": "FD6",
			"category_group_name": "음식점",
			"category_name": "음식점 \u003e 아시아음식 \u003e 동남아음식",
			"distance": "2356",
			"id": "665690561",
			"phone": "02-501-0798",
			"place_name": "포엠쓰리 대치동본점",
			"place_url": "http://place.map.kakao.com/665690561",
			"road_address_name": "서울 강남구 남부순환로 2927",
			"x": "127.06037681621831",
			"y": "37.49363766965981"
		},
		{
			"address_name": "서울 강남구 세곡동 590",
			"category_group_code": "FD6",
			"category_group_name": "음식점",
			"category_name": "음식점 \u003e 아시아음식 \u003e 동남아음식",
			"distance": "2364",
			"id": "104640479",
			"phone": "02-2226-5556",
			"place_name": "포아이니 강남세곡점",
			"place_url": "http://place.map.kakao.com/104640479",
			"road_address_name": "서울 강남구 헌릉로569길 13",
			"x": "127.100049092209",
			"y": "37.4668174350783"
		}
	],
	"meta": {
		"is_end": false,
		"pageable_count": 45,
		"same_name": {
			"keyword": "쌀국수",
			"region": [],
			"selected_region": ""
		},
		"total_count": 190
	}
}